listmodel
