Metadata-Version: 1.0
Name: listmodel
Version: 0.2.1
Summary: Listmodel is a Python library for object mappings for various list sources (XML documents, CSV documents, text documents, JSON/YAML objects) in a unified manner.
Home-page: http://github.com/jackuess/listmodel
Author: Jacques de Laval
Author-email: jacques@tuttosport.se
License: LGPL v3
Platform: UNKNOWN
